cumulusci/__about__.py
cumulusci/__init__.py
cumulusci/__main__.py
cumulusci/conftest.py
cumulusci/cumulusci.yml
cumulusci/cli/__init__.py
cumulusci/cli/cci.py
cumulusci/cli/error.py
cumulusci/cli/flow.py
cumulusci/cli/logger.py
cumulusci/cli/org.py
cumulusci/cli/plan.py
cumulusci/cli/project.py
cumulusci/cli/robot.py
cumulusci/cli/runtime.py
cumulusci/cli/service.py
cumulusci/cli/task.py
cumulusci/cli/ui.py
cumulusci/cli/utils.py
cumulusci/cli/tests/__init__.py
cumulusci/cli/tests/test_cci.py
cumulusci/cli/tests/test_error.py
cumulusci/cli/tests/test_flow.py
cumulusci/cli/tests/test_logger.py
cumulusci/cli/tests/test_org.py
cumulusci/cli/tests/test_plan.py
cumulusci/cli/tests/test_project.py
cumulusci/cli/tests/test_robot.py
cumulusci/cli/tests/test_runtime.py
cumulusci/cli/tests/test_service.py
cumulusci/cli/tests/test_task.py
cumulusci/cli/tests/test_ui.py
cumulusci/cli/tests/test_utils.py
cumulusci/cli/tests/utils.py
cumulusci/core/__init__.py
cumulusci/core/datasets.py
cumulusci/core/debug.py
cumulusci/core/enums.py
cumulusci/core/exceptions.py
cumulusci/core/flowrunner.py
cumulusci/core/github.py
cumulusci/core/runtime.py
cumulusci/core/sfdx.py
cumulusci/core/tasks.py
cumulusci/core/template_utils.py
cumulusci/core/utils.py
cumulusci/core/versions.py
cumulusci/core/config/BaseConfig.py
cumulusci/core/config/BaseTaskFlowConfig.py
cumulusci/core/config/OrgConfig.py
cumulusci/core/config/ScratchOrgConfig.py
cumulusci/core/config/__init__.py
cumulusci/core/config/base_config.py
cumulusci/core/config/base_task_flow_config.py
cumulusci/core/config/marketing_cloud_service_config.py
cumulusci/core/config/oauth2_service_config.py
cumulusci/core/config/org_config.py
cumulusci/core/config/project_config.py
cumulusci/core/config/scratch_org_config.py
cumulusci/core/config/sfdx_org_config.py
cumulusci/core/config/universal_config.py
cumulusci/core/config/util.py
cumulusci/core/config/tests/_test_config_backwards_compatibility.py
cumulusci/core/config/tests/test_config.py
cumulusci-4.8.1.dist-info/METADATA
cumulusci-4.8.1.dist-info/WHEEL
cumulusci-4.8.1.dist-info/entry_points.txt
cumulusci-4.8.1.dist-info/licenses/AUTHORS.rst
cumulusci-4.8.1.dist-info/licenses/LICENSE
cumulusci-4.8.1.dist-info/RECORD
